folium_vectortilelayer/__init__.py
folium_vectortilelayer/vectortilelayer.py
folium_vectortilelayer-0.2.5.dist-info/METADATA
folium_vectortilelayer-0.2.5.dist-info/WHEEL
folium_vectortilelayer-0.2.5.dist-info/licenses/LICENSE
folium_vectortilelayer-0.2.5.dist-info/RECORD
