Metadata-Version: 2.4
Name: folium-vectortilelayer
Version: 0.2.5
Summary: VectorTileLayer plugin for folium
Project-URL: Homepage, https://iwpnd.github.io/folium-vectortilelayer/
Project-URL: Repository, https://github.com/iwpnd/folium-vectortilelayer
Project-URL: Documentation, https://iwpnd.github.io/folium-vectortilelayer/
Author-email: Benjamin Ramser <iwpnd@posteo.de>
License-File: LICENSE
Keywords: python
Classifier: Intended Audience :: Developers
Classifier: Programming Language :: Python
Classifier: Programming Language :: Python :: 3
Classifier: Programming Language :: Python :: 3.10
Classifier: Programming Language :: Python :: 3.11
Classifier: Programming Language :: Python :: 3.12
Classifier: Programming Language :: Python :: 3.13
Classifier: Topic :: Software Development :: Libraries :: Python Modules
Requires-Python: <4.0,>=3.10
Requires-Dist: folium>=0.19.5
